anti_header/__init__.py
anti_header/exceptions.py
anti_header/headers.py
anti_header/utils/__init__.py
anti_header/utils/datatypes.py
anti_header/utils/http.py
anti_header/utils/log.py
anti_header/utils/python.py
anti_header-0.0.6.dist-info/LICENSE
anti_header-0.0.6.dist-info/METADATA
anti_header-0.0.6.dist-info/WHEEL
anti_header-0.0.6.dist-info/top_level.txt
anti_header-0.0.6.dist-info/RECORD
