Metadata-Version: 2.1
Name: anti-header
Version: 0.0.6
Summary: fake chrome, firefox, opera browser header anti header
Home-page: https://github.com/ihandmine/anti-header
Author: handmine
Author-email: handmine@outlook.com
License: MIT
Keywords: header,headers,crawl header,fake,fake header,browser,spider header,anti,anti header,scrapy header
Platform: UNKNOWN
Classifier: License :: OSI Approved :: MIT License
Classifier: Programming Language :: Python
Classifier: Intended Audience :: Developers
Classifier: Operating System :: OS Independent
Requires-Python: >=3.7.0
Requires-Dist: anti-useragent
